djangoquran2/__init__.py
djangoquran2/apps.py
djangoquran2/buckwalter.py
djangoquran2/models.py
djangoquran2/urls.py
djangoquran2/views.py
djangoquran2/datas/lemmas.csv
djangoquran2/datas/words.csv
djangoquran2/management/__init__.py
djangoquran2/management/commands/__init__.py
djangoquran2/management/commands/loadquran.py
djangoquran2/migrations/0001_initial.py
djangoquran2/migrations/__init__.py
djangoquran2/static/djangoquran2/Scheherazade-R.woff
djangoquran2/static/djangoquran2/bootstrap.css
djangoquran2/static/djangoquran2/speaker.ico
djangoquran2/static/djangoquran2/style.css
djangoquran2/static/djangoquran2/audio/readme.md
djangoquran2/templates/djangoquran2/_table.html
djangoquran2/templates/djangoquran2/base.html
djangoquran2/templates/djangoquran2/index.html
djangoquran2/templates/djangoquran2/root.html
djangoquran2/templates/djangoquran2/root_list.html
djangoquran2/templates/djangoquran2/surah.html
djangoquran2/templates/djangoquran2/word.html
djangoquran2/templatetags/__init__.py
djangoquran2/templatetags/extra_filters.py
djangoquran2-0.3.dist-info/METADATA
djangoquran2-0.3.dist-info/WHEEL
djangoquran2-0.3.dist-info/top_level.txt
djangoquran2-0.3.dist-info/RECORD
